gimad-0.0.1.dist-info/METADATA
gimad-0.0.1.dist-info/WHEEL
gimad-0.0.1.dist-info/entry_points.txt
gimad/__init__.py
gimad/_commands/__init__.py
gimad/_commands/down.py
gimad/_commands/init.py
gimad/_commands/new.py
gimad/_commands/redo.py
gimad/_commands/up.py
gimad/_config.py
gimad/_db.py
gimad/_runner.py
gimad/_template.py
gimad/_utils.py
gimad-0.0.1.dist-info/RECORD
