Metadata-Version: 2.1
Name: gimad
Version: 0.0.1
Summary: Non-schema database migration tool for PostgreSQL
Author-Email: Chau Duong <duongdominhchau@gmail.com>
Requires-Python: >=3.12
Requires-Dist: psycopg[binary]
Requires-Dist: typer
Requires-Dist: pydantic-settings
